databrowser/__init__.py
databrowser/data_browser.css
databrowser/data_browser.py
databrowser/widgets/__init__.py
databrowser/widgets/_directory_filter_tree.py
databrowser-0.38.1.dist-info/LICENSE
databrowser-0.38.1.dist-info/METADATA
databrowser-0.38.1.dist-info/WHEEL
databrowser-0.38.1.dist-info/entry_points.txt
databrowser-0.38.1.dist-info/RECORD
