Metadata-Version: 2.1
Name: databrowser
Version: 0.38.1
Summary: Quick tool to browse and view data files (json,csv,parquet,more) on local disk and s3
Home-page: https://github.com/jverhoeks/databrowser
License: MIT
Author: Jacob Verhoeks
Author-email: jacob.verhoeks@gmail.com
Requires-Python: >=3.9,<4.0
Classifier: License :: OSI Approved :: MIT License
Classifier: Programming Language :: Python :: 3
Classifier: Programming Language :: Python :: 3.9
Classifier: Programming Language :: Python :: 3.10
Classifier: Programming Language :: Python :: 3.11
Requires-Dist: beautifulsoup4 (>=4.12.2,<5.0.0)
Requires-Dist: html5lib (>=1.1,<2.0)
Requires-Dist: lxml (>=5.1.0,<6.0.0)
Requires-Dist: pandas (>=1.5.2,<3.0.0)
Requires-Dist: pyarrow (>=5.0.0)
Requires-Dist: s3fs (>=2024.3.1,<2025.0.0)
Requires-Dist: s3path (>=0.4.1,<0.6.0)
Requires-Dist: textual (>=0.54.0,<0.55.0)
Requires-Dist: xlrd (>=2.0.1,<3.0.0)
Project-URL: Repository, https://github.com/jverhoeks/databrowser
